CHANGES
LICENSE
MANIFEST.in
README.rst
setup.cfg
setup.py
pyramid_webforms/__init__.py
pyramid_webforms/api.py
pyramid_webforms.egg-info/PKG-INFO
pyramid_webforms.egg-info/SOURCES.txt
pyramid_webforms.egg-info/dependency_links.txt
pyramid_webforms.egg-info/requires.txt
pyramid_webforms.egg-info/top_level.txt
pyramid_webforms/locale/de/LC_MESSAGES/pyramid_webforms.mo
pyramid_webforms/locale/ru/LC_MESSAGES/pyramid_webforms.mo
pyramid_webforms/templates/field.p_wf_mako
pyramid_webforms/templates/field_error.p_wf_mako
pyramid_webforms/templates/fieldset.p_wf_mako
pyramid_webforms/templates/form.p_wf_mako
pyramid_webforms/templates/form_error.p_wf_mako
pyramid_webforms/templates/submit.p_wf_mako
pyramid_webforms/templates/submit_alternate.p_wf_mako
pyramid_webforms/templates/tooltip.p_wf_mako