Metadata-Version: 1.1
Name: pyramid-webforms
Version: 0.0.2
Summary: Simple declarative web forms using FormEncode and WebHelpers
Home-page: https://github.com/avanov/pyramid_webforms
Author: Maxim Avanov
Author-email: maxim.avanov@gmail.com
License: MIT
Download-URL: https://github.com/avanov/pyramid_webforms
Keywords: pyramid formencode forms templates validation
Platform: UNKNOWN
Classifier: Development Status :: 2 - Pre-Alpha
Classifier: Environment :: Web Environment
Classifier: Framework :: Pyramid
Classifier: Intended Audience :: Developers
Classifier: License :: OSI Approved
Classifier: License :: OSI Approved :: MIT License
Classifier: Operating System :: MacOS
Classifier: Operating System :: Microsoft
Classifier: Operating System :: POSIX
Classifier: Programming Language :: Python
Classifier: Programming Language :: Python :: 2.7
Classifier: Topic :: Internet :: WWW/HTTP
Classifier: Topic :: Internet :: WWW/HTTP :: Dynamic Content
Classifier: Topic :: Software Development :: Libraries :: Python Modules
